{
  "url": "https://ladyzenko.ru/tpost/7rv4hv4821-detskii-psihologicheskii-rai",
  "slug": "tpost-7rv4hv4821-detskii-psihologicheskii-rai",
  "title": "Детский психологический рай",
  "meta_description": "",
  "meta_keywords": "",
  "h1": [
    "Детский психологический рай"
  ],
  "headings": [
    {
      "level": "h1",
      "text": "Детский психологический рай"
    }
  ],
  "text": "",
  "paragraphs": [],
  "popups": [],
  "images": [
    "https://static.tildacdn.com/tild3666-3438-4263-b838-383961663532/5228950588291679200.jpg",
    "https://static.tildacdn.com/img/tildacopy.png"
  ],
  "files": [],
  "videos": [],
  "contacts": [],
  "links": [
    "https://ladyzenko.ru",
    "https://tilda.cc/"
  ],
  "canonical": "https://ladyzenko.ru/tpost/7rv4hv4821-detskii-psihologicheskii-rai",
  "og_image": "https://static.tildacdn.com/tild3666-3438-4263-b838-383961663532/5228950588291679200.jpg"
}